selected_area/__init__.py
selected_area/area.py
tests/__init__.py
tests/test_area.py
selected_area-0.1.1.dist-info/LICENSE
selected_area-0.1.1.dist-info/METADATA
selected_area-0.1.1.dist-info/WHEEL
selected_area-0.1.1.dist-info/top_level.txt
selected_area-0.1.1.dist-info/RECORD
