Metadata-Version: 2.1
Name: selected-area
Version: 0.1.1
Summary: Calculates if plot/segment intersects the selected area.
Home-page: https://github.com/nedvedikd/selected-area
Author: Dominik Nedvedik
Author-email: dominik.nedvedik@protonmail.com
License: UNKNOWN
Platform: UNKNOWN
Classifier: Programming Language :: Python :: 3.8
Classifier: License :: OSI Approved :: MIT License
Classifier: Operating System :: OS Independent
Requires-Python: >=3.8
